flameai/__init__.py
flameai/__main__.py
flameai/_env.py
flameai/cmd.py
flameai/hive.py
flameai/metrics.py
flameai/mining.py
flameai/plot.py
flameai/preprocessing.py
flameai/sql.py
flameai/train.py
flameai/util.py
flameai-1.0.9.dist-info/METADATA
flameai-1.0.9.dist-info/WHEEL
flameai-1.0.9.dist-info/entry_points.txt
flameai-1.0.9.dist-info/licenses/LICENSE
flameai-1.0.9.dist-info/RECORD
